{
  "company": "Happy Cog",
  "type": [],
  "url": "http://www.happycog.com/",
  "webSiteUrl": "http://www.happycog.com/",
  "technologies": [],
  "locations": {
    "philadelphia": {
      "@context": "http://schema.org",
      "@type": "Place",
      "address": "1315 Walnut St, Philadelphia, PA 19107",
      "geo": {
        "@context": "http://schema.org",
        "@type": "Place",
        "latitude": 39.949591,
        "longitude": -75.16289
      }
    }
  },
  "positions": [
    {
      "@context": "http://schema.org",
      "@type": "JobPosting",
      "employmentType": "full-time",
      "title": "Designer",
      "alternateName": "",
      "url": "http://www.happycog.com/",
      "jobLocation": "philadelphia",
      "remote": false,
      "datePosted": "2016-01-05"
    },
    {
      "@context": "http://schema.org",
      "@type": "JobPosting",
      "employmentType": "full-time",
      "title": "Senior Designer",
      "alternateName": "",
      "url": "http://www.happycog.com/",
      "jobLocation": "philadelphia",
      "remote": false,
      "datePosted": "2016-01-05"
    }
  ]
}
