{
  "company": "Lamps.com Inc",
  "type": [],
  "url": "http://jobs.interactivecommercegroup.com/",
  "webSiteUrl": "http://www.lamps.com/",
  "technologies": [],
  "locations": {
    "philadelphia": {
      "@context": "http://schema.org",
      "@type": "Place",
      "address": "1217 Sansom St, Floor 8, Philadelphia, PA 19107",
      "geo": {
        "@context": "http://schema.org",
        "@type": "Place",
        "latitude": 39.949923,
        "longitude": -75.161334
      }
    }
  },
  "positions": [
    {
      "@context": "http://schema.org",
      "@type": "JobPosting",
      "employmentType": "full-time",
      "title": "eCommerce Merchandiser",
      "alternateName": "",
      "url": "http://jobs.interactivecommercegroup.com/",
      "jobLocation": "philadelphia",
      "remote": false,
      "datePosted": ""
    },
    {
      "@context": "http://schema.org",
      "@type": "JobPosting",
      "employmentType": "full-time",
      "title": "Full Stack Magento Developer",
      "alternateName": "",
      "url": "http://jobs.interactivecommercegroup.com/",
      "jobLocation": "philadelphia",
      "remote": false,
      "datePosted": ""
    },
    {
      "@context": "http://schema.org",
      "@type": "JobPosting",
      "employmentType": "full-time",
      "title": "Product Data Specialist",
      "alternateName": "",
      "url": "http://jobs.interactivecommercegroup.com/",
      "jobLocation": "philadelphia",
      "remote": false,
      "datePosted": ""
    }
  ]
}
