{
  "company": "Philly Marketing Labs",
  "type": [
    "consultancy"
  ],
  "url": "http://www.phillymarketinglabs.com/join-our-team/",
  "webSiteUrl": "http://www.phillymarketinglabs.com/",
  "technologies": [],
  "locations": {
    "wayne": {
      "@context": "http://schema.org",
      "@type": "Place",
      "address": "224 Lansdowne Ave, Wayne, PA 19087",
      "geo": {
        "@context": "http://schema.org",
        "@type": "Place",
        "latitude": 40.040375898,
        "longitude": -75.3892247755
      }
    }
  },
  "positions": [
    {
      "@context": "http://schema.org",
      "@type": "JobPosting",
      "employmentType": "full-time",
      "title": "Web Marketing Project Manager",
      "alternateName": "Project Manager",
      "url": "http://www.phillymarketinglabs.com/about/join-our-team/web-marketing-project-manager/",
      "jobLocation": "wayne",
      "remote": false,
      "datePosted": "2016-04-28"
    },
    {
      "@context": "http://schema.org",
      "@type": "JobPosting",
      "employmentType": "full-time",
      "title": "Organic Search Manager",
      "alternateName": "Content Strategy, SEO",
      "url": "http://www.phillymarketinglabs.com/about/join-our-team/organic-search-manager/",
      "jobLocation": "wayne",
      "remote": false,
      "datePosted": "2016-04-28"
    },
    {
      "@context": "http://schema.org",
      "@type": "JobPosting",
      "employmentType": "full-time",
      "title": "Senior Digital Marketing Project Manager",
      "alternateName": "Project Manager",
      "url": "http://www.phillymarketinglabs.com/about/join-our-team/senior-digital-marketing-project-manager/",
      "jobLocation": "wayne",
      "remote": false,
      "datePosted": "2016-04-28"
    },
    {
      "@context": "http://schema.org",
      "@type": "JobPosting",
      "datePosted": "2016-07-17",
      "employmentType": "full-time",
      "jobLocation": "wayne",
      "remote": false,
      "title": "Senior Paid Search Manager",
      "url": "http://www.phillymarketinglabs.com/about/join-our-team/paid-search-manager/"
    }
  ],
  "updated": "2016-04-28"
}
